{
  "userProfileId": 34745850,
  "totalKilocalories": 2359.0,
  "activeKilocalories": 240.0,
  "bmrKilocalories": 2119.0,
  "wellnessKilocalories": 2359.0,
  "burnedKilocalories": null,
  "consumedKilocalories": null,
  "remainingKilocalories": null,
  "totalSteps": 5424,
  "netCalorieGoal": null,
  "totalDistanceMeters": 4393,
  "wellnessDistanceMeters": 4393,
  "wellnessActiveKilocalories": 240.0,
  "netRemainingKilocalories": 240.0,
  "userDailySummaryId": 34745850,
  "calendarDate": "2026-04-17",
  "rule": {
    "typeId": 4,
    "typeKey": "groups"
  },
  "uuid": "63d5d6c373d540b7baf696a0ed964aed",
  "dailyStepGoal": 2860,
  "wellnessStartTimeGmt": "2026-04-16T22:00:00.0",
  "wellnessStartTimeLocal": "2026-04-17T00:00:00.0",
  "wellnessEndTimeGmt": "2026-04-17T22:00:00.0",
  "wellnessEndTimeLocal": "2026-04-18T00:00:00.0",
  "durationInMilliseconds": 86400000,
  "wellnessDescription": null,
  "highlyActiveSeconds": 797,
  "activeSeconds": 5588,
  "sedentarySeconds": 53255,
  "sleepingSeconds": 26760,
  "includesWellnessData": true,
  "includesActivityData": false,
  "includesCalorieConsumedData": false,
  "privacyProtected": false,
  "moderateIntensityMinutes": 0,
  "vigorousIntensityMinutes": 0,
  "floorsAscendedInMeters": 24.828,
  "floorsDescendedInMeters": 20.786,
  "floorsAscended": 8.14567,
  "floorsDescended": 6.81955,
  "intensityMinutesGoal": 150,
  "userFloorsAscendedGoal": 10,
  "minHeartRate": 51,
  "maxHeartRate": 108,
  "restingHeartRate": 53,
  "lastSevenDaysAvgRestingHeartRate": 53,
  "source": "GARMIN",
  "averageStressLevel": 36,
  "maxStressLevel": 93,
  "stressDuration": 45780,
  "restStressDuration": 30360,
  "activityStressDuration": 7980,
  "uncategorizedStressDuration": 2280,
  "totalStressDuration": 86400,
  "lowStressDuration": 25320,
  "mediumStressDuration": 16980,
  "highStressDuration": 3480,
  "stressPercentage": 52.99,
  "restStressPercentage": 35.14,
  "activityStressPercentage": 9.24,
  "uncategorizedStressPercentage": 2.64,
  "lowStressPercentage": 29.31,
  "mediumStressPercentage": 19.65,
  "highStressPercentage": 4.03,
  "stressQualifier": "STRESSFUL",
  "measurableAwakeDuration": 60960,
  "measurableAsleepDuration": 23160,
  "lastSyncTimestampGMT": null,
  "minAvgHeartRate": 52,
  "maxAvgHeartRate": 108,
  "bodyBatteryChargedValue": 46,
  "bodyBatteryDrainedValue": 85,
  "bodyBatteryHighestValue": 100,
  "bodyBatteryLowestValue": 15,
  "bodyBatteryMostRecentValue": 15,
  "bodyBatteryDuringSleep": 56,
  "bodyBatteryAtWakeTime": 100,
  "bodyBatteryVersion": 2.0,
  "abnormalHeartRateAlertsCount": null,
  "averageSpo2": null,
  "lowestSpo2": null,
  "latestSpo2": null,
  "latestSpo2ReadingTimeGmt": null,
  "latestSpo2ReadingTimeLocal": null,
  "averageMonitoringEnvironmentAltitude": 90.0,
  "restingCaloriesFromActivity": null,
  "avgWakingRespirationValue": 14.0,
  "highestRespirationValue": 19.0,
  "lowestRespirationValue": 10.0,
  "latestRespirationValue": 14.0,
  "latestRespirationTimeGMT": "2026-04-17T22:00:00.0",
  "respirationAlgorithmVersion": 100
}