{
  "userProfilePK": 34745850,
  "calendarDate": "2026-05-07",
  "startTimestampGMT": "2026-05-06T22:00:00.0",
  "endTimestampGMT": "2026-05-07T22:00:00.0",
  "startTimestampLocal": "2026-05-07T00:00:00.0",
  "endTimestampLocal": "2026-05-08T00:00:00.0",
  "maxStressLevel": 92,
  "avgStressLevel": 27,
  "stressChartValueOffset": 1,
  "stressChartYAxisOrigin": -1,
  "stressValueDescriptorsDTOList": [
    {
      "index": 0,
      "key": "timestamp"
    },
    {
      "index": 1,
      "key": "stressLevel"
    }
  ],
  "stressValuesArray": [
    [
      1778104800000,
      25
    ],
    [
      1778104980000,
      26
    ],
    [
      1778105160000,
      19
    ],
    [
      1778105340000,
      24
    ],
    [
      1778105520000,
      22
    ],
    [
      1778105700000,
      25
    ],
    [
      1778105880000,
      24
    ],
    [
      1778106060000,
      24
    ],
    [
      1778106240000,
      24
    ],
    [
      1778106420000,
      22
    ],
    [
      1778106600000,
      24
    ],
    [
      1778106780000,
      24
    ],
    [
      1778106960000,
      25
    ],
    [
      1778107140000,
      24
    ],
    [
      1778107320000,
      21
    ],
    [
      1778107500000,
      23
    ],
    [
      1778107680000,
      23
    ],
    [
      1778107860000,
      17
    ],
    [
      1778108040000,
      18
    ],
    [
      1778108220000,
      19
    ],
    [
      1778108400000,
      18
    ],
    [
      1778108580000,
      16
    ],
    [
      1778108760000,
      16
    ],
    [
      1778108940000,
      16
    ],
    [
      1778109120000,
      15
    ],
    [
      1778109300000,
      15
    ],
    [
      1778109480000,
      15
    ],
    [
      1778109660000,
      13
    ],
    [
      1778109840000,
      11
    ],
    [
      1778110020000,
      9
    ],
    [
      1778110200000,
      12
    ],
    [
      1778110380000,
      12
    ],
    [
      1778110560000,
      18
    ],
    [
      1778110740000,
      21
    ],
    [
      1778110920000,
      19
    ],
    [
      1778111100000,
      13
    ],
    [
      1778111280000,
      13
    ],
    [
      1778111460000,
      12
    ],
    [
      1778111640000,
      13
    ],
    [
      1778111820000,
      11
    ],
    [
      1778112000000,
      10
    ],
    [
      1778112180000,
      7
    ],
    [
      1778112360000,
      9
    ],
    [
      1778112540000,
      15
    ],
    [
      1778112720000,
      14
    ],
    [
      1778112900000,
      14
    ],
    [
      1778113080000,
      12
    ],
    [
      1778113260000,
      10
    ],
    [
      1778113440000,
      13
    ],
    [
      1778113620000,
      12
    ],
    [
      1778113800000,
      19
    ],
    [
      1778113980000,
      17
    ],
    [
      1778114160000,
      12
    ],
    [
      1778114340000,
      15
    ],
    [
      1778114520000,
      17
    ],
    [
      1778114700000,
      16
    ],
    [
      1778114880000,
      16
    ],
    [
      1778115060000,
      17
    ],
    [
      1778115240000,
      14
    ],
    [
      1778115420000,
      18
    ],
    [
      1778115600000,
      16
    ],
    [
      1778115780000,
      15
    ],
    [
      1778115960000,
      14
    ],
    [
      1778116140000,
      16
    ],
    [
      1778116320000,
      19
    ],
    [
      1778116500000,
      19
    ],
    [
      1778116680000,
      20
    ],
    [
      1778116860000,
      20
    ],
    [
      1778117040000,
      18
    ],
    [
      1778117220000,
      20
    ],
    [
      1778117400000,
      19
    ],
    [
      1778117580000,
      18
    ],
    [
      1778117760000,
      19
    ],
    [
      1778117940000,
      10
    ],
    [
      1778118120000,
      11
    ],
    [
      1778118300000,
      16
    ],
    [
      1778118480000,
      10
    ],
    [
      1778118660000,
      14
    ],
    [
      1778118840000,
      11
    ],
    [
      1778119020000,
      10
    ],
    [
      1778119200000,
      15
    ],
    [
      1778119380000,
      16
    ],
    [
      1778119560000,
      15
    ],
    [
      1778119740000,
      13
    ],
    [
      1778119920000,
      14
    ],
    [
      1778120100000,
      11
    ],
    [
      1778120280000,
      15
    ],
    [
      1778120460000,
      11
    ],
    [
      1778120640000,
      13
    ],
    [
      1778120820000,
      15
    ],
    [
      1778121000000,
      12
    ],
    [
      1778121180000,
      12
    ],
    [
      1778121360000,
      15
    ],
    [
      1778121540000,
      16
    ],
    [
      1778121720000,
      16
    ],
    [
      1778121900000,
      16
    ],
    [
      1778122080000,
      17
    ],
    [
      1778122260000,
      12
    ],
    [
      1778122440000,
      9
    ],
    [
      1778122620000,
      13
    ],
    [
      1778122800000,
      13
    ],
    [
      1778122980000,
      13
    ],
    [
      1778123160000,
      15
    ],
    [
      1778123340000,
      12
    ],
    [
      1778123520000,
      18
    ],
    [
      1778123700000,
      10
    ],
    [
      1778123880000,
      11
    ],
    [
      1778124060000,
      12
    ],
    [
      1778124240000,
      14
    ],
    [
      1778124420000,
      16
    ],
    [
      1778124600000,
      15
    ],
    [
      1778124780000,
      13
    ],
    [
      1778124960000,
      17
    ],
    [
      1778125140000,
      16
    ],
    [
      1778125320000,
      16
    ],
    [
      1778125500000,
      16
    ],
    [
      1778125680000,
      18
    ],
    [
      1778125860000,
      18
    ],
    [
      1778126040000,
      19
    ],
    [
      1778126220000,
      15
    ],
    [
      1778126400000,
      10
    ],
    [
      1778126580000,
      12
    ],
    [
      1778126760000,
      10
    ],
    [
      1778126940000,
      12
    ],
    [
      1778127120000,
      10
    ],
    [
      1778127300000,
      11
    ],
    [
      1778127480000,
      13
    ],
    [
      1778127660000,
      11
    ],
    [
      1778127840000,
      13
    ],
    [
      1778128020000,
      23
    ],
    [
      1778128200000,
      -1
    ],
    [
      1778128380000,
      40
    ],
    [
      1778128560000,
      -1
    ],
    [
      1778128740000,
      -1
    ],
    [
      1778128920000,
      -1
    ],
    [
      1778129100000,
      -1
    ],
    [
      1778129280000,
      -1
    ],
    [
      1778129460000,
      -1
    ],
    [
      1778129640000,
      19
    ],
    [
      1778129820000,
      28
    ],
    [
      1778130000000,
      17
    ],
    [
      1778130180000,
      -2
    ],
    [
      1778130360000,
      -1
    ],
    [
      1778130540000,
      13
    ],
    [
      1778130720000,
      24
    ],
    [
      1778130900000,
      47
    ],
    [
      1778131080000,
      23
    ],
    [
      1778131260000,
      29
    ],
    [
      1778131440000,
      -1
    ],
    [
      1778131620000,
      23
    ],
    [
      1778131800000,
      41
    ],
    [
      1778131980000,
      23
    ],
    [
      1778132160000,
      30
    ],
    [
      1778132340000,
      28
    ],
    [
      1778132520000,
      36
    ],
    [
      1778132700000,
      28
    ],
    [
      1778132880000,
      28
    ],
    [
      1778133060000,
      29
    ],
    [
      1778133240000,
      29
    ],
    [
      1778133420000,
      -1
    ],
    [
      1778133600000,
      27
    ],
    [
      1778133780000,
      50
    ],
    [
      1778133960000,
      23
    ],
    [
      1778134140000,
      25
    ],
    [
      1778134320000,
      32
    ],
    [
      1778134500000,
      37
    ],
    [
      1778134680000,
      30
    ],
    [
      1778134860000,
      30
    ],
    [
      1778135040000,
      26
    ],
    [
      1778135220000,
      33
    ],
    [
      1778135400000,
      33
    ],
    [
      1778135580000,
      28
    ],
    [
      1778135760000,
      23
    ],
    [
      1778135940000,
      25
    ],
    [
      1778136120000,
      22
    ],
    [
      1778136300000,
      21
    ],
    [
      1778136480000,
      22
    ],
    [
      1778136660000,
      24
    ],
    [
      1778136840000,
      -1
    ],
    [
      1778137020000,
      44
    ],
    [
      1778137200000,
      -1
    ],
    [
      1778137380000,
      -1
    ],
    [
      1778137560000,
      28
    ],
    [
      1778137740000,
      21
    ],
    [
      1778137920000,
      19
    ],
    [
      1778138100000,
      19
    ],
    [
      1778138280000,
      18
    ],
    [
      1778138460000,
      18
    ],
    [
      1778138640000,
      24
    ],
    [
      1778138820000,
      24
    ],
    [
      1778139000000,
      25
    ],
    [
      1778139180000,
      -1
    ],
    [
      1778139360000,
      -2
    ],
    [
      1778139540000,
      -1
    ],
    [
      1778139720000,
      43
    ],
    [
      1778139900000,
      38
    ],
    [
      1778140080000,
      -1
    ],
    [
      1778140260000,
      18
    ],
    [
      1778140440000,
      8
    ],
    [
      1778140620000,
      19
    ],
    [
      1778140800000,
      22
    ],
    [
      1778140980000,
      25
    ],
    [
      1778141160000,
      25
    ],
    [
      1778141340000,
      20
    ],
    [
      1778141520000,
      25
    ],
    [
      1778141700000,
      24
    ],
    [
      1778141880000,
      22
    ],
    [
      1778142060000,
      23
    ],
    [
      1778142240000,
      26
    ],
    [
      1778142420000,
      29
    ],
    [
      1778142600000,
      24
    ],
    [
      1778142780000,
      16
    ],
    [
      1778142960000,
      20
    ],
    [
      1778143140000,
      25
    ],
    [
      1778143320000,
      22
    ],
    [
      1778143500000,
      23
    ],
    [
      1778143680000,
      24
    ],
    [
      1778143860000,
      22
    ],
    [
      1778144040000,
      23
    ],
    [
      1778144220000,
      -1
    ],
    [
      1778144400000,
      -1
    ],
    [
      1778144580000,
      32
    ],
    [
      1778144760000,
      19
    ],
    [
      1778144940000,
      23
    ],
    [
      1778145120000,
      15
    ],
    [
      1778145300000,
      12
    ],
    [
      1778145480000,
      19
    ],
    [
      1778145660000,
      32
    ],
    [
      1778145840000,
      -2
    ],
    [
      1778146020000,
      55
    ],
    [
      1778146200000,
      25
    ],
    [
      1778146380000,
      34
    ],
    [
      1778146560000,
      32
    ],
    [
      1778146740000,
      -1
    ],
    [
      1778146920000,
      -1
    ],
    [
      1778147100000,
      31
    ],
    [
      1778147280000,
      16
    ],
    [
      1778147460000,
      15
    ],
    [
      1778147640000,
      11
    ],
    [
      1778147820000,
      19
    ],
    [
      1778148000000,
      25
    ],
    [
      1778148180000,
      33
    ],
    [
      1778148360000,
      31
    ],
    [
      1778148540000,
      28
    ],
    [
      1778148720000,
      44
    ],
    [
      1778148900000,
      34
    ],
    [
      1778149080000,
      34
    ],
    [
      1778149260000,
      42
    ],
    [
      1778149440000,
      45
    ],
    [
      1778149620000,
      42
    ],
    [
      1778149800000,
      44
    ],
    [
      1778149980000,
      36
    ],
    [
      1778150160000,
      31
    ],
    [
      1778150340000,
      34
    ],
    [
      1778150520000,
      -2
    ],
    [
      1778150700000,
      -1
    ],
    [
      1778150880000,
      55
    ],
    [
      1778151060000,
      58
    ],
    [
      1778151240000,
      34
    ],
    [
      1778151420000,
      23
    ],
    [
      1778151600000,
      23
    ],
    [
      1778151780000,
      22
    ],
    [
      1778151960000,
      22
    ],
    [
      1778152140000,
      25
    ],
    [
      1778152320000,
      27
    ],
    [
      1778152500000,
      25
    ],
    [
      1778152680000,
      25
    ],
    [
      1778152860000,
      33
    ],
    [
      1778153040000,
      46
    ],
    [
      1778153220000,
      31
    ],
    [
      1778153400000,
      -1
    ],
    [
      1778153580000,
      46
    ],
    [
      1778153760000,
      20
    ],
    [
      1778153940000,
      -1
    ],
    [
      1778154120000,
      64
    ],
    [
      1778154300000,
      25
    ],
    [
      1778154480000,
      49
    ],
    [
      1778154660000,
      40
    ],
    [
      1778154840000,
      45
    ],
    [
      1778155020000,
      50
    ],
    [
      1778155200000,
      -1
    ],
    [
      1778155380000,
      55
    ],
    [
      1778155560000,
      61
    ],
    [
      1778155740000,
      -1
    ],
    [
      1778155920000,
      27
    ],
    [
      1778156100000,
      28
    ],
    [
      1778156280000,
      34
    ],
    [
      1778156460000,
      33
    ],
    [
      1778156640000,
      37
    ],
    [
      1778156820000,
      35
    ],
    [
      1778157000000,
      34
    ],
    [
      1778157180000,
      32
    ],
    [
      1778157360000,
      36
    ],
    [
      1778157540000,
      31
    ],
    [
      1778157720000,
      28
    ],
    [
      1778157900000,
      47
    ],
    [
      1778158080000,
      52
    ],
    [
      1778158260000,
      44
    ],
    [
      1778158440000,
      42
    ],
    [
      1778158620000,
      45
    ],
    [
      1778158800000,
      41
    ],
    [
      1778158980000,
      31
    ],
    [
      1778159160000,
      40
    ],
    [
      1778159340000,
      52
    ],
    [
      1778159520000,
      48
    ],
    [
      1778159700000,
      57
    ],
    [
      1778159880000,
      34
    ],
    [
      1778160060000,
      -1
    ],
    [
      1778160240000,
      -1
    ],
    [
      1778160420000,
      24
    ],
    [
      1778160600000,
      23
    ],
    [
      1778160780000,
      22
    ],
    [
      1778160960000,
      28
    ],
    [
      1778161140000,
      28
    ],
    [
      1778161320000,
      29
    ],
    [
      1778161500000,
      52
    ],
    [
      1778161680000,
      31
    ],
    [
      1778161860000,
      28
    ],
    [
      1778162040000,
      29
    ],
    [
      1778162220000,
      31
    ],
    [
      1778162400000,
      25
    ],
    [
      1778162580000,
      47
    ],
    [
      1778162760000,
      -2
    ],
    [
      1778162940000,
      -1
    ],
    [
      1778163120000,
      64
    ],
    [
      1778163300000,
      64
    ],
    [
      1778163480000,
      83
    ],
    [
      1778163660000,
      23
    ],
    [
      1778163840000,
      14
    ],
    [
      1778164020000,
      35
    ],
    [
      1778164200000,
      17
    ],
    [
      1778164380000,
      21
    ],
    [
      1778164560000,
      21
    ],
    [
      1778164740000,
      19
    ],
    [
      1778164920000,
      -1
    ],
    [
      1778165100000,
      23
    ],
    [
      1778165280000,
      21
    ],
    [
      1778165460000,
      -1
    ],
    [
      1778165640000,
      -1
    ],
    [
      1778165820000,
      -1
    ],
    [
      1778166000000,
      29
    ],
    [
      1778166180000,
      -1
    ],
    [
      1778166360000,
      -1
    ],
    [
      1778166540000,
      29
    ],
    [
      1778166720000,
      23
    ],
    [
      1778166900000,
      30
    ],
    [
      1778167080000,
      25
    ],
    [
      1778167260000,
      24
    ],
    [
      1778167440000,
      30
    ],
    [
      1778167620000,
      36
    ],
    [
      1778167800000,
      31
    ],
    [
      1778167980000,
      29
    ],
    [
      1778168160000,
      31
    ],
    [
      1778168340000,
      34
    ],
    [
      1778168520000,
      37
    ],
    [
      1778168700000,
      37
    ],
    [
      1778168880000,
      43
    ],
    [
      1778169060000,
      43
    ],
    [
      1778169240000,
      33
    ],
    [
      1778169420000,
      58
    ],
    [
      1778169600000,
      43
    ],
    [
      1778169780000,
      39
    ],
    [
      1778169960000,
      44
    ],
    [
      1778170140000,
      49
    ],
    [
      1778170320000,
      64
    ],
    [
      1778170500000,
      68
    ],
    [
      1778170680000,
      -1
    ],
    [
      1778170860000,
      -1
    ],
    [
      1778171040000,
      48
    ],
    [
      1778171220000,
      44
    ],
    [
      1778171400000,
      38
    ],
    [
      1778171580000,
      40
    ],
    [
      1778171760000,
      30
    ],
    [
      1778171940000,
      24
    ],
    [
      1778172120000,
      27
    ],
    [
      1778172300000,
      21
    ],
    [
      1778172480000,
      25
    ],
    [
      1778172660000,
      24
    ],
    [
      1778172840000,
      25
    ],
    [
      1778173020000,
      27
    ],
    [
      1778173200000,
      25
    ],
    [
      1778173380000,
      25
    ],
    [
      1778173560000,
      25
    ],
    [
      1778173740000,
      24
    ],
    [
      1778173920000,
      26
    ],
    [
      1778174100000,
      37
    ],
    [
      1778174280000,
      63
    ],
    [
      1778174460000,
      -2
    ],
    [
      1778174640000,
      51
    ],
    [
      1778174820000,
      25
    ],
    [
      1778175000000,
      24
    ],
    [
      1778175180000,
      39
    ],
    [
      1778175360000,
      -1
    ],
    [
      1778175540000,
      24
    ],
    [
      1778175720000,
      23
    ],
    [
      1778175900000,
      28
    ],
    [
      1778176080000,
      26
    ],
    [
      1778176260000,
      28
    ],
    [
      1778176440000,
      29
    ],
    [
      1778176620000,
      28
    ],
    [
      1778176800000,
      28
    ],
    [
      1778176980000,
      27
    ],
    [
      1778177160000,
      24
    ],
    [
      1778177340000,
      19
    ],
    [
      1778177520000,
      25
    ],
    [
      1778177700000,
      24
    ],
    [
      1778177880000,
      -1
    ],
    [
      1778178060000,
      -1
    ],
    [
      1778178240000,
      43
    ],
    [
      1778178420000,
      23
    ],
    [
      1778178600000,
      21
    ],
    [
      1778178780000,
      22
    ],
    [
      1778178960000,
      23
    ],
    [
      1778179140000,
      22
    ],
    [
      1778179320000,
      23
    ],
    [
      1778179500000,
      28
    ],
    [
      1778179680000,
      24
    ],
    [
      1778179860000,
      25
    ],
    [
      1778180040000,
      25
    ],
    [
      1778180220000,
      24
    ],
    [
      1778180400000,
      45
    ],
    [
      1778180580000,
      44
    ],
    [
      1778180760000,
      -1
    ],
    [
      1778180940000,
      72
    ],
    [
      1778181120000,
      52
    ],
    [
      1778181300000,
      37
    ],
    [
      1778181480000,
      40
    ],
    [
      1778181660000,
      34
    ],
    [
      1778181840000,
      43
    ],
    [
      1778182020000,
      57
    ],
    [
      1778182200000,
      64
    ],
    [
      1778182380000,
      41
    ],
    [
      1778182560000,
      42
    ],
    [
      1778182740000,
      35
    ],
    [
      1778182920000,
      40
    ],
    [
      1778183100000,
      37
    ],
    [
      1778183280000,
      35
    ],
    [
      1778183460000,
      38
    ],
    [
      1778183640000,
      37
    ],
    [
      1778183820000,
      34
    ],
    [
      1778184000000,
      72
    ],
    [
      1778184180000,
      -2
    ],
    [
      1778184360000,
      -1
    ],
    [
      1778184540000,
      26
    ],
    [
      1778184720000,
      28
    ],
    [
      1778184900000,
      29
    ],
    [
      1778185080000,
      31
    ],
    [
      1778185260000,
      24
    ],
    [
      1778185440000,
      30
    ],
    [
      1778185620000,
      31
    ],
    [
      1778185800000,
      31
    ],
    [
      1778185980000,
      28
    ],
    [
      1778186160000,
      31
    ],
    [
      1778186340000,
      30
    ],
    [
      1778186520000,
      31
    ],
    [
      1778186700000,
      35
    ],
    [
      1778186880000,
      37
    ],
    [
      1778187060000,
      30
    ],
    [
      1778187240000,
      25
    ],
    [
      1778187420000,
      25
    ],
    [
      1778187600000,
      31
    ],
    [
      1778187780000,
      28
    ],
    [
      1778187960000,
      25
    ],
    [
      1778188140000,
      31
    ],
    [
      1778188320000,
      28
    ],
    [
      1778188500000,
      29
    ],
    [
      1778188680000,
      31
    ],
    [
      1778188860000,
      31
    ],
    [
      1778189040000,
      30
    ],
    [
      1778189220000,
      34
    ],
    [
      1778189400000,
      33
    ],
    [
      1778189580000,
      34
    ],
    [
      1778189760000,
      35
    ],
    [
      1778189940000,
      35
    ],
    [
      1778190120000,
      35
    ],
    [
      1778190300000,
      35
    ],
    [
      1778190480000,
      36
    ],
    [
      1778190660000,
      35
    ],
    [
      1778190840000,
      37
    ],
    [
      1778191020000,
      36
    ]
  ],
  "bodyBatteryValueDescriptorsDTOList": [
    {
      "bodyBatteryValueDescriptorIndex": 0,
      "bodyBatteryValueDescriptorKey": "timestamp"
    },
    {
      "bodyBatteryValueDescriptorIndex": 1,
      "bodyBatteryValueDescriptorKey": "bodyBatteryStatus"
    },
    {
      "bodyBatteryValueDescriptorIndex": 2,
      "bodyBatteryValueDescriptorKey": "bodyBatteryLevel"
    },
    {
      "bodyBatteryValueDescriptorIndex": 3,
      "bodyBatteryValueDescriptorKey": "bodyBatteryVersion"
    }
  ],
  "bodyBatteryValuesArray": [
    [
      1778104800000,
      "MEASURED",
      34,
      2.0
    ],
    [
      1778104980000,
      "MEASURED",
      34,
      2.0
    ],
    [
      1778105160000,
      "MEASURED",
      35,
      2.0
    ],
    [
      1778105340000,
      "MEASURED",
      35,
      2.0
    ],
    [
      1778105520000,
      "MEASURED",
      35,
      2.0
    ],
    [
      1778105700000,
      "MEASURED",
      36,
      2.0
    ],
    [
      1778105880000,
      "MEASURED",
      37,
      2.0
    ],
    [
      1778106060000,
      "MEASURED",
      37,
      2.0
    ],
    [
      1778106240000,
      "MEASURED",
      37,
      2.0
    ],
    [
      1778106420000,
      "MEASURED",
      38,
      2.0
    ],
    [
      1778106600000,
      "MEASURED",
      38,
      2.0
    ],
    [
      1778106780000,
      "MEASURED",
      39,
      2.0
    ],
    [
      1778106960000,
      "MEASURED",
      39,
      2.0
    ],
    [
      1778107140000,
      "MEASURED",
      39,
      2.0
    ],
    [
      1778107320000,
      "MEASURED",
      40,
      2.0
    ],
    [
      1778107500000,
      "MEASURED",
      40,
      2.0
    ],
    [
      1778107680000,
      "MEASURED",
      41,
      2.0
    ],
    [
      1778107860000,
      "MEASURED",
      42,
      2.0
    ],
    [
      1778108040000,
      "MEASURED",
      42,
      2.0
    ],
    [
      1778108220000,
      "MEASURED",
      43,
      2.0
    ],
    [
      1778108400000,
      "MEASURED",
      43,
      2.0
    ],
    [
      1778108580000,
      "MEASURED",
      44,
      2.0
    ],
    [
      1778108760000,
      "MEASURED",
      45,
      2.0
    ],
    [
      1778108940000,
      "MEASURED",
      46,
      2.0
    ],
    [
      1778109120000,
      "MEASURED",
      46,
      2.0
    ],
    [
      1778109300000,
      "MEASURED",
      47,
      2.0
    ],
    [
      1778109480000,
      "MEASURED",
      48,
      2.0
    ],
    [
      1778109660000,
      "MEASURED",
      48,
      2.0
    ],
    [
      1778109840000,
      "MEASURED",
      49,
      2.0
    ],
    [
      1778110020000,
      "MEASURED",
      49,
      2.0
    ],
    [
      1778110200000,
      "MEASURED",
      50,
      2.0
    ],
    [
      1778110380000,
      "MEASURED",
      50,
      2.0
    ],
    [
      1778110560000,
      "MEASURED",
      51,
      2.0
    ],
    [
      1778110740000,
      "MEASURED",
      51,
      2.0
    ],
    [
      1778110920000,
      "MEASURED",
      51,
      2.0
    ],
    [
      1778111100000,
      "MEASURED",
      52,
      2.0
    ],
    [
      1778111280000,
      "MEASURED",
      52,
      2.0
    ],
    [
      1778111460000,
      "MEASURED",
      53,
      2.0
    ],
    [
      1778111640000,
      "MEASURED",
      53,
      2.0
    ],
    [
      1778111820000,
      "MEASURED",
      54,
      2.0
    ],
    [
      1778112000000,
      "MEASURED",
      55,
      2.0
    ],
    [
      1778112180000,
      "MEASURED",
      55,
      2.0
    ],
    [
      1778112360000,
      "MEASURED",
      56,
      2.0
    ],
    [
      1778112540000,
      "MEASURED",
      57,
      2.0
    ],
    [
      1778112720000,
      "MEASURED",
      57,
      2.0
    ],
    [
      1778112900000,
      "MEASURED",
      57,
      2.0
    ],
    [
      1778113080000,
      "MEASURED",
      58,
      2.0
    ],
    [
      1778113260000,
      "MEASURED",
      58,
      2.0
    ],
    [
      1778113440000,
      "MEASURED",
      59,
      2.0
    ],
    [
      1778113620000,
      "MEASURED",
      59,
      2.0
    ],
    [
      1778113800000,
      "MEASURED",
      61,
      2.0
    ],
    [
      1778113980000,
      "MEASURED",
      61,
      2.0
    ],
    [
      1778114160000,
      "MEASURED",
      61,
      2.0
    ],
    [
      1778114340000,
      "MEASURED",
      61,
      2.0
    ],
    [
      1778114520000,
      "MEASURED",
      62,
      2.0
    ],
    [
      1778114700000,
      "MEASURED",
      62,
      2.0
    ],
    [
      1778114880000,
      "MEASURED",
      63,
      2.0
    ],
    [
      1778115060000,
      "MEASURED",
      63,
      2.0
    ],
    [
      1778115240000,
      "MEASURED",
      64,
      2.0
    ],
    [
      1778115420000,
      "MEASURED",
      64,
      2.0
    ],
    [
      1778115600000,
      "MEASURED",
      64,
      2.0
    ],
    [
      1778115780000,
      "MEASURED",
      65,
      2.0
    ],
    [
      1778115960000,
      "MEASURED",
      66,
      2.0
    ],
    [
      1778116140000,
      "MEASURED",
      66,
      2.0
    ],
    [
      1778116320000,
      "MEASURED",
      66,
      2.0
    ],
    [
      1778116500000,
      "MEASURED",
      67,
      2.0
    ],
    [
      1778116680000,
      "MEASURED",
      67,
      2.0
    ],
    [
      1778116860000,
      "MEASURED",
      67,
      2.0
    ],
    [
      1778117040000,
      "MEASURED",
      67,
      2.0
    ],
    [
      1778117220000,
      "MEASURED",
      68,
      2.0
    ],
    [
      1778117400000,
      "MEASURED",
      68,
      2.0
    ],
    [
      1778117580000,
      "MEASURED",
      68,
      2.0
    ],
    [
      1778117760000,
      "MEASURED",
      68,
      2.0
    ],
    [
      1778117940000,
      "MEASURED",
      69,
      2.0
    ],
    [
      1778118120000,
      "MEASURED",
      69,
      2.0
    ],
    [
      1778118300000,
      "MEASURED",
      69,
      2.0
    ],
    [
      1778118480000,
      "MEASURED",
      70,
      2.0
    ],
    [
      1778118660000,
      "MEASURED",
      70,
      2.0
    ],
    [
      1778118840000,
      "MEASURED",
      71,
      2.0
    ],
    [
      1778119020000,
      "MEASURED",
      71,
      2.0
    ],
    [
      1778119200000,
      "MEASURED",
      72,
      2.0
    ],
    [
      1778119380000,
      "MEASURED",
      73,
      2.0
    ],
    [
      1778119560000,
      "MEASURED",
      73,
      2.0
    ],
    [
      1778119740000,
      "MEASURED",
      73,
      2.0
    ],
    [
      1778119920000,
      "MEASURED",
      73,
      2.0
    ],
    [
      1778120100000,
      "MEASURED",
      74,
      2.0
    ],
    [
      1778120280000,
      "MEASURED",
      74,
      2.0
    ],
    [
      1778120460000,
      "MEASURED",
      74,
      2.0
    ],
    [
      1778120640000,
      "MEASURED",
      75,
      2.0
    ],
    [
      1778120820000,
      "MEASURED",
      75,
      2.0
    ],
    [
      1778121000000,
      "MEASURED",
      75,
      2.0
    ],
    [
      1778121180000,
      "MEASURED",
      76,
      2.0
    ],
    [
      1778121360000,
      "MEASURED",
      76,
      2.0
    ],
    [
      1778121540000,
      "MEASURED",
      77,
      2.0
    ],
    [
      1778121720000,
      "MEASURED",
      77,
      2.0
    ],
    [
      1778121900000,
      "MEASURED",
      77,
      2.0
    ],
    [
      1778122080000,
      "MEASURED",
      78,
      2.0
    ],
    [
      1778122260000,
      "MEASURED",
      78,
      2.0
    ],
    [
      1778122440000,
      "MEASURED",
      78,
      2.0
    ],
    [
      1778122620000,
      "MEASURED",
      79,
      2.0
    ],
    [
      1778122800000,
      "MEASURED",
      79,
      2.0
    ],
    [
      1778122980000,
      "MEASURED",
      79,
      2.0
    ],
    [
      1778123160000,
      "MEASURED",
      80,
      2.0
    ],
    [
      1778123340000,
      "MEASURED",
      80,
      2.0
    ],
    [
      1778123520000,
      "MEASURED",
      80,
      2.0
    ],
    [
      1778123700000,
      "MEASURED",
      80,
      2.0
    ],
    [
      1778123880000,
      "MEASURED",
      81,
      2.0
    ],
    [
      1778124060000,
      "MEASURED",
      81,
      2.0
    ],
    [
      1778124240000,
      "MEASURED",
      81,
      2.0
    ],
    [
      1778124420000,
      "MEASURED",
      82,
      2.0
    ],
    [
      1778124600000,
      "MEASURED",
      82,
      2.0
    ],
    [
      1778124780000,
      "MEASURED",
      82,
      2.0
    ],
    [
      1778124960000,
      "MEASURED",
      82,
      2.0
    ],
    [
      1778125140000,
      "MEASURED",
      82,
      2.0
    ],
    [
      1778125320000,
      "MEASURED",
      82,
      2.0
    ],
    [
      1778125500000,
      "MEASURED",
      82,
      2.0
    ],
    [
      1778125680000,
      "MEASURED",
      83,
      2.0
    ],
    [
      1778125860000,
      "MEASURED",
      83,
      2.0
    ],
    [
      1778126040000,
      "MEASURED",
      83,
      2.0
    ],
    [
      1778126220000,
      "MEASURED",
      83,
      2.0
    ],
    [
      1778126400000,
      "MEASURED",
      83,
      2.0
    ],
    [
      1778126580000,
      "MEASURED",
      83,
      2.0
    ],
    [
      1778126760000,
      "MEASURED",
      84,
      2.0
    ],
    [
      1778126940000,
      "MEASURED",
      84,
      2.0
    ],
    [
      1778127120000,
      "MEASURED",
      84,
      2.0
    ],
    [
      1778127300000,
      "MEASURED",
      84,
      2.0
    ],
    [
      1778127480000,
      "MEASURED",
      84,
      2.0
    ],
    [
      1778127660000,
      "MEASURED",
      84,
      2.0
    ],
    [
      1778127840000,
      "MEASURED",
      85,
      2.0
    ],
    [
      1778128020000,
      "MEASURED",
      85,
      2.0
    ],
    [
      1778128200000,
      "MEASURED",
      85,
      2.0
    ],
    [
      1778128380000,
      "MEASURED",
      85,
      2.0
    ],
    [
      1778128560000,
      "MEASURED",
      85,
      2.0
    ],
    [
      1778128740000,
      "MEASURED",
      85,
      2.0
    ],
    [
      1778128920000,
      "MODELED",
      84,
      2.0
    ],
    [
      1778129100000,
      "MODELED",
      84,
      2.0
    ],
    [
      1778129280000,
      "MODELED",
      84,
      2.0
    ],
    [
      1778129460000,
      "MEASURED",
      82,
      2.0
    ],
    [
      1778129640000,
      "MEASURED",
      82,
      2.0
    ],
    [
      1778129820000,
      "MEASURED",
      82,
      2.0
    ],
    [
      1778130000000,
      "MEASURED",
      82,
      2.0
    ],
    [
      1778130180000,
      "MEASURED",
      82,
      2.0
    ],
    [
      1778130360000,
      "MEASURED",
      82,
      2.0
    ],
    [
      1778130540000,
      "MEASURED",
      82,
      2.0
    ],
    [
      1778130720000,
      "MEASURED",
      82,
      2.0
    ],
    [
      1778130900000,
      "MEASURED",
      81,
      2.0
    ],
    [
      1778131080000,
      "MEASURED",
      81,
      2.0
    ],
    [
      1778131260000,
      "MEASURED",
      81,
      2.0
    ],
    [
      1778131440000,
      "MEASURED",
      80,
      2.0
    ],
    [
      1778131620000,
      "MEASURED",
      80,
      2.0
    ],
    [
      1778131800000,
      "MEASURED",
      79,
      2.0
    ],
    [
      1778131980000,
      "MEASURED",
      79,
      2.0
    ],
    [
      1778132160000,
      "MEASURED",
      79,
      2.0
    ],
    [
      1778132340000,
      "MEASURED",
      79,
      2.0
    ],
    [
      1778132520000,
      "MEASURED",
      78,
      2.0
    ],
    [
      1778132700000,
      "MEASURED",
      78,
      2.0
    ],
    [
      1778132880000,
      "MEASURED",
      78,
      2.0
    ],
    [
      1778133060000,
      "MEASURED",
      78,
      2.0
    ],
    [
      1778133240000,
      "MEASURED",
      78,
      2.0
    ],
    [
      1778133420000,
      "MEASURED",
      77,
      2.0
    ],
    [
      1778133600000,
      "MEASURED",
      77,
      2.0
    ],
    [
      1778133780000,
      "MEASURED",
      77,
      2.0
    ],
    [
      1778133960000,
      "MEASURED",
      77,
      2.0
    ],
    [
      1778134140000,
      "MEASURED",
      76,
      2.0
    ],
    [
      1778134320000,
      "MEASURED",
      76,
      2.0
    ],
    [
      1778134500000,
      "MEASURED",
      76,
      2.0
    ],
    [
      1778134680000,
      "MEASURED",
      76,
      2.0
    ],
    [
      1778134860000,
      "MEASURED",
      75,
      2.0
    ],
    [
      1778135040000,
      "MEASURED",
      75,
      2.0
    ],
    [
      1778135220000,
      "MEASURED",
      75,
      2.0
    ],
    [
      1778135400000,
      "MEASURED",
      75,
      2.0
    ],
    [
      1778135580000,
      "MEASURED",
      75,
      2.0
    ],
    [
      1778135760000,
      "MEASURED",
      75,
      2.0
    ],
    [
      1778135940000,
      "MEASURED",
      74,
      2.0
    ],
    [
      1778136120000,
      "MEASURED",
      74,
      2.0
    ],
    [
      1778136300000,
      "MEASURED",
      74,
      2.0
    ],
    [
      1778136480000,
      "MEASURED",
      73,
      2.0
    ],
    [
      1778136660000,
      "MEASURED",
      73,
      2.0
    ],
    [
      1778136840000,
      "MEASURED",
      73,
      2.0
    ],
    [
      1778137020000,
      "MEASURED",
      73,
      2.0
    ],
    [
      1778137200000,
      "MEASURED",
      72,
      2.0
    ],
    [
      1778137380000,
      "MEASURED",
      72,
      2.0
    ],
    [
      1778137560000,
      "MEASURED",
      72,
      2.0
    ],
    [
      1778137740000,
      "MEASURED",
      72,
      2.0
    ],
    [
      1778137920000,
      "MEASURED",
      72,
      2.0
    ],
    [
      1778138100000,
      "MEASURED",
      72,
      2.0
    ],
    [
      1778138280000,
      "MEASURED",
      72,
      2.0
    ],
    [
      1778138460000,
      "MEASURED",
      72,
      2.0
    ],
    [
      1778138640000,
      "MEASURED",
      71,
      2.0
    ],
    [
      1778138820000,
      "MEASURED",
      71,
      2.0
    ],
    [
      1778139000000,
      "MEASURED",
      71,
      2.0
    ],
    [
      1778139180000,
      "MEASURED",
      71,
      2.0
    ],
    [
      1778139360000,
      "MEASURED",
      70,
      2.0
    ],
    [
      1778139540000,
      "MEASURED",
      70,
      2.0
    ],
    [
      1778139720000,
      "MEASURED",
      70,
      2.0
    ],
    [
      1778139900000,
      "MEASURED",
      69,
      2.0
    ],
    [
      1778140080000,
      "MEASURED",
      69,
      2.0
    ],
    [
      1778140260000,
      "MEASURED",
      69,
      2.0
    ],
    [
      1778140440000,
      "MEASURED",
      69,
      2.0
    ],
    [
      1778140620000,
      "MEASURED",
      69,
      2.0
    ],
    [
      1778140800000,
      "MEASURED",
      69,
      2.0
    ],
    [
      1778140980000,
      "MEASURED",
      69,
      2.0
    ],
    [
      1778141160000,
      "MEASURED",
      69,
      2.0
    ],
    [
      1778141340000,
      "MEASURED",
      69,
      2.0
    ],
    [
      1778141520000,
      "MEASURED",
      69,
      2.0
    ],
    [
      1778141700000,
      "MEASURED",
      69,
      2.0
    ],
    [
      1778141880000,
      "MEASURED",
      68,
      2.0
    ],
    [
      1778142060000,
      "MEASURED",
      68,
      2.0
    ],
    [
      1778142240000,
      "MEASURED",
      68,
      2.0
    ],
    [
      1778142420000,
      "MEASURED",
      68,
      2.0
    ],
    [
      1778142600000,
      "MEASURED",
      68,
      2.0
    ],
    [
      1778142780000,
      "MEASURED",
      67,
      2.0
    ],
    [
      1778142960000,
      "MEASURED",
      67,
      2.0
    ],
    [
      1778143140000,
      "MEASURED",
      67,
      2.0
    ],
    [
      1778143320000,
      "MEASURED",
      67,
      2.0
    ],
    [
      1778143500000,
      "MEASURED",
      67,
      2.0
    ],
    [
      1778143680000,
      "MEASURED",
      67,
      2.0
    ],
    [
      1778143860000,
      "MEASURED",
      67,
      2.0
    ],
    [
      1778144040000,
      "MEASURED",
      67,
      2.0
    ],
    [
      1778144220000,
      "MEASURED",
      67,
      2.0
    ],
    [
      1778144400000,
      "MEASURED",
      67,
      2.0
    ],
    [
      1778144580000,
      "MEASURED",
      66,
      2.0
    ],
    [
      1778144760000,
      "MEASURED",
      66,
      2.0
    ],
    [
      1778144940000,
      "MEASURED",
      66,
      2.0
    ],
    [
      1778145120000,
      "MEASURED",
      66,
      2.0
    ],
    [
      1778145300000,
      "MEASURED",
      66,
      2.0
    ],
    [
      1778145480000,
      "MEASURED",
      66,
      2.0
    ],
    [
      1778145660000,
      "MEASURED",
      66,
      2.0
    ],
    [
      1778145840000,
      "MEASURED",
      65,
      2.0
    ],
    [
      1778146020000,
      "MEASURED",
      65,
      2.0
    ],
    [
      1778146200000,
      "MEASURED",
      65,
      2.0
    ],
    [
      1778146380000,
      "MEASURED",
      64,
      2.0
    ],
    [
      1778146560000,
      "MEASURED",
      64,
      2.0
    ],
    [
      1778146740000,
      "MEASURED",
      64,
      2.0
    ],
    [
      1778146920000,
      "MEASURED",
      63,
      2.0
    ],
    [
      1778147100000,
      "MEASURED",
      63,
      2.0
    ],
    [
      1778147280000,
      "MEASURED",
      63,
      2.0
    ],
    [
      1778147460000,
      "MEASURED",
      63,
      2.0
    ],
    [
      1778147640000,
      "MEASURED",
      63,
      2.0
    ],
    [
      1778147820000,
      "MEASURED",
      63,
      2.0
    ],
    [
      1778148000000,
      "MEASURED",
      63,
      2.0
    ],
    [
      1778148180000,
      "MEASURED",
      63,
      2.0
    ],
    [
      1778148360000,
      "MEASURED",
      62,
      2.0
    ],
    [
      1778148540000,
      "MEASURED",
      62,
      2.0
    ],
    [
      1778148720000,
      "MEASURED",
      62,
      2.0
    ],
    [
      1778148900000,
      "MEASURED",
      62,
      2.0
    ],
    [
      1778149080000,
      "MEASURED",
      61,
      2.0
    ],
    [
      1778149260000,
      "MEASURED",
      61,
      2.0
    ],
    [
      1778149440000,
      "MEASURED",
      61,
      2.0
    ],
    [
      1778149620000,
      "MEASURED",
      61,
      2.0
    ],
    [
      1778149800000,
      "MEASURED",
      60,
      2.0
    ],
    [
      1778149980000,
      "MEASURED",
      60,
      2.0
    ],
    [
      1778150160000,
      "MEASURED",
      60,
      2.0
    ],
    [
      1778150340000,
      "MEASURED",
      60,
      2.0
    ],
    [
      1778150520000,
      "MEASURED",
      59,
      2.0
    ],
    [
      1778150700000,
      "MEASURED",
      59,
      2.0
    ],
    [
      1778150880000,
      "MEASURED",
      59,
      2.0
    ],
    [
      1778151060000,
      "MEASURED",
      58,
      2.0
    ],
    [
      1778151240000,
      "MEASURED",
      58,
      2.0
    ],
    [
      1778151420000,
      "MEASURED",
      58,
      2.0
    ],
    [
      1778151600000,
      "MEASURED",
      58,
      2.0
    ],
    [
      1778151780000,
      "MEASURED",
      58,
      2.0
    ],
    [
      1778151960000,
      "MEASURED",
      58,
      2.0
    ],
    [
      1778152140000,
      "MEASURED",
      57,
      2.0
    ],
    [
      1778152320000,
      "MEASURED",
      57,
      2.0
    ],
    [
      1778152500000,
      "MEASURED",
      57,
      2.0
    ],
    [
      1778152680000,
      "MEASURED",
      57,
      2.0
    ],
    [
      1778152860000,
      "MEASURED",
      57,
      2.0
    ],
    [
      1778153040000,
      "MEASURED",
      56,
      2.0
    ],
    [
      1778153220000,
      "MEASURED",
      56,
      2.0
    ],
    [
      1778153400000,
      "MEASURED",
      56,
      2.0
    ],
    [
      1778153580000,
      "MEASURED",
      56,
      2.0
    ],
    [
      1778153760000,
      "MEASURED",
      56,
      2.0
    ],
    [
      1778153940000,
      "MEASURED",
      56,
      2.0
    ],
    [
      1778154120000,
      "MEASURED",
      55,
      2.0
    ],
    [
      1778154300000,
      "MEASURED",
      55,
      2.0
    ],
    [
      1778154480000,
      "MEASURED",
      55,
      2.0
    ],
    [
      1778154660000,
      "MEASURED",
      54,
      2.0
    ],
    [
      1778154840000,
      "MEASURED",
      54,
      2.0
    ],
    [
      1778155020000,
      "MEASURED",
      54,
      2.0
    ],
    [
      1778155200000,
      "MEASURED",
      54,
      2.0
    ],
    [
      1778155380000,
      "MEASURED",
      53,
      2.0
    ],
    [
      1778155560000,
      "MEASURED",
      53,
      2.0
    ],
    [
      1778155740000,
      "MEASURED",
      53,
      2.0
    ],
    [
      1778155920000,
      "MEASURED",
      53,
      2.0
    ],
    [
      1778156100000,
      "MEASURED",
      52,
      2.0
    ],
    [
      1778156280000,
      "MEASURED",
      52,
      2.0
    ],
    [
      1778156460000,
      "MEASURED",
      52,
      2.0
    ],
    [
      1778156640000,
      "MEASURED",
      51,
      2.0
    ],
    [
      1778156820000,
      "MEASURED",
      51,
      2.0
    ],
    [
      1778157000000,
      "MEASURED",
      51,
      2.0
    ],
    [
      1778157180000,
      "MEASURED",
      51,
      2.0
    ],
    [
      1778157360000,
      "MEASURED",
      51,
      2.0
    ],
    [
      1778157540000,
      "MEASURED",
      50,
      2.0
    ],
    [
      1778157720000,
      "MEASURED",
      50,
      2.0
    ],
    [
      1778157900000,
      "MEASURED",
      50,
      2.0
    ],
    [
      1778158080000,
      "MEASURED",
      50,
      2.0
    ],
    [
      1778158260000,
      "MEASURED",
      50,
      2.0
    ],
    [
      1778158440000,
      "MEASURED",
      49,
      2.0
    ],
    [
      1778158620000,
      "MEASURED",
      49,
      2.0
    ],
    [
      1778158800000,
      "MEASURED",
      49,
      2.0
    ],
    [
      1778158980000,
      "MEASURED",
      49,
      2.0
    ],
    [
      1778159160000,
      "MEASURED",
      49,
      2.0
    ],
    [
      1778159340000,
      "MEASURED",
      48,
      2.0
    ],
    [
      1778159520000,
      "MEASURED",
      47,
      2.0
    ],
    [
      1778159700000,
      "MEASURED",
      47,
      2.0
    ],
    [
      1778159880000,
      "MEASURED",
      47,
      2.0
    ],
    [
      1778160060000,
      "MEASURED",
      47,
      2.0
    ],
    [
      1778160240000,
      "MEASURED",
      47,
      2.0
    ],
    [
      1778160420000,
      "MEASURED",
      46,
      2.0
    ],
    [
      1778160600000,
      "MEASURED",
      46,
      2.0
    ],
    [
      1778160780000,
      "MEASURED",
      46,
      2.0
    ],
    [
      1778160960000,
      "MEASURED",
      46,
      2.0
    ],
    [
      1778161140000,
      "MEASURED",
      46,
      2.0
    ],
    [
      1778161320000,
      "MEASURED",
      46,
      2.0
    ],
    [
      1778161500000,
      "MEASURED",
      46,
      2.0
    ],
    [
      1778161680000,
      "MEASURED",
      46,
      2.0
    ],
    [
      1778161860000,
      "MEASURED",
      46,
      2.0
    ],
    [
      1778162040000,
      "MEASURED",
      45,
      2.0
    ],
    [
      1778162220000,
      "MEASURED",
      45,
      2.0
    ],
    [
      1778162400000,
      "MEASURED",
      45,
      2.0
    ],
    [
      1778162580000,
      "MEASURED",
      45,
      2.0
    ],
    [
      1778162760000,
      "MEASURED",
      45,
      2.0
    ],
    [
      1778162940000,
      "MEASURED",
      44,
      2.0
    ],
    [
      1778163120000,
      "MEASURED",
      44,
      2.0
    ],
    [
      1778163300000,
      "MEASURED",
      44,
      2.0
    ],
    [
      1778163480000,
      "MEASURED",
      43,
      2.0
    ],
    [
      1778163660000,
      "MEASURED",
      43,
      2.0
    ],
    [
      1778163840000,
      "MEASURED",
      43,
      2.0
    ],
    [
      1778164020000,
      "MEASURED",
      43,
      2.0
    ],
    [
      1778164200000,
      "MEASURED",
      43,
      2.0
    ],
    [
      1778164380000,
      "MEASURED",
      43,
      2.0
    ],
    [
      1778164560000,
      "MEASURED",
      43,
      2.0
    ],
    [
      1778164740000,
      "MEASURED",
      43,
      2.0
    ],
    [
      1778164920000,
      "MEASURED",
      43,
      2.0
    ],
    [
      1778165100000,
      "MEASURED",
      43,
      2.0
    ],
    [
      1778165280000,
      "MEASURED",
      43,
      2.0
    ],
    [
      1778165460000,
      "MEASURED",
      43,
      2.0
    ],
    [
      1778165640000,
      "MEASURED",
      43,
      2.0
    ],
    [
      1778165820000,
      "MEASURED",
      43,
      2.0
    ],
    [
      1778166000000,
      "MEASURED",
      43,
      2.0
    ],
    [
      1778166180000,
      "MEASURED",
      42,
      2.0
    ],
    [
      1778166360000,
      "MEASURED",
      42,
      2.0
    ],
    [
      1778166540000,
      "MEASURED",
      42,
      2.0
    ],
    [
      1778166720000,
      "MEASURED",
      42,
      2.0
    ],
    [
      1778166900000,
      "MEASURED",
      42,
      2.0
    ],
    [
      1778167080000,
      "MEASURED",
      42,
      2.0
    ],
    [
      1778167260000,
      "MEASURED",
      42,
      2.0
    ],
    [
      1778167440000,
      "MEASURED",
      42,
      2.0
    ],
    [
      1778167620000,
      "MEASURED",
      42,
      2.0
    ],
    [
      1778167800000,
      "MEASURED",
      41,
      2.0
    ],
    [
      1778167980000,
      "MEASURED",
      41,
      2.0
    ],
    [
      1778168160000,
      "MEASURED",
      41,
      2.0
    ],
    [
      1778168340000,
      "MEASURED",
      41,
      2.0
    ],
    [
      1778168520000,
      "MEASURED",
      41,
      2.0
    ],
    [
      1778168700000,
      "MEASURED",
      41,
      2.0
    ],
    [
      1778168880000,
      "MEASURED",
      41,
      2.0
    ],
    [
      1778169060000,
      "MEASURED",
      40,
      2.0
    ],
    [
      1778169240000,
      "MEASURED",
      40,
      2.0
    ],
    [
      1778169420000,
      "MEASURED",
      40,
      2.0
    ],
    [
      1778169600000,
      "MEASURED",
      40,
      2.0
    ],
    [
      1778169780000,
      "MEASURED",
      40,
      2.0
    ],
    [
      1778169960000,
      "MEASURED",
      39,
      2.0
    ],
    [
      1778170140000,
      "MEASURED",
      39,
      2.0
    ],
    [
      1778170320000,
      "MEASURED",
      39,
      2.0
    ],
    [
      1778170500000,
      "MEASURED",
      38,
      2.0
    ],
    [
      1778170680000,
      "MEASURED",
      38,
      2.0
    ],
    [
      1778170860000,
      "MEASURED",
      38,
      2.0
    ],
    [
      1778171040000,
      "MEASURED",
      37,
      2.0
    ],
    [
      1778171220000,
      "MEASURED",
      37,
      2.0
    ],
    [
      1778171400000,
      "MEASURED",
      37,
      2.0
    ],
    [
      1778171580000,
      "MEASURED",
      37,
      2.0
    ],
    [
      1778171760000,
      "MEASURED",
      37,
      2.0
    ],
    [
      1778171940000,
      "MEASURED",
      37,
      2.0
    ],
    [
      1778172120000,
      "MEASURED",
      36,
      2.0
    ],
    [
      1778172300000,
      "MEASURED",
      36,
      2.0
    ],
    [
      1778172480000,
      "MEASURED",
      36,
      2.0
    ],
    [
      1778172660000,
      "MEASURED",
      36,
      2.0
    ],
    [
      1778172840000,
      "MEASURED",
      36,
      2.0
    ],
    [
      1778173020000,
      "MEASURED",
      36,
      2.0
    ],
    [
      1778173200000,
      "MEASURED",
      36,
      2.0
    ],
    [
      1778173380000,
      "MEASURED",
      36,
      2.0
    ],
    [
      1778173560000,
      "MEASURED",
      35,
      2.0
    ],
    [
      1778173740000,
      "MEASURED",
      35,
      2.0
    ],
    [
      1778173920000,
      "MEASURED",
      35,
      2.0
    ],
    [
      1778174100000,
      "MEASURED",
      35,
      2.0
    ],
    [
      1778174280000,
      "MEASURED",
      35,
      2.0
    ],
    [
      1778174460000,
      "MEASURED",
      35,
      2.0
    ],
    [
      1778174640000,
      "MEASURED",
      35,
      2.0
    ],
    [
      1778174820000,
      "MEASURED",
      35,
      2.0
    ],
    [
      1778175000000,
      "MEASURED",
      34,
      2.0
    ],
    [
      1778175180000,
      "MEASURED",
      34,
      2.0
    ],
    [
      1778175360000,
      "MEASURED",
      34,
      2.0
    ],
    [
      1778175540000,
      "MEASURED",
      34,
      2.0
    ],
    [
      1778175720000,
      "MEASURED",
      34,
      2.0
    ],
    [
      1778175900000,
      "MEASURED",
      34,
      2.0
    ],
    [
      1778176080000,
      "MEASURED",
      34,
      2.0
    ],
    [
      1778176260000,
      "MEASURED",
      34,
      2.0
    ],
    [
      1778176440000,
      "MEASURED",
      34,
      2.0
    ],
    [
      1778176620000,
      "MEASURED",
      34,
      2.0
    ],
    [
      1778176800000,
      "MEASURED",
      34,
      2.0
    ],
    [
      1778176980000,
      "MEASURED",
      34,
      2.0
    ],
    [
      1778177160000,
      "MEASURED",
      34,
      2.0
    ],
    [
      1778177340000,
      "MEASURED",
      34,
      2.0
    ],
    [
      1778177520000,
      "MEASURED",
      34,
      2.0
    ],
    [
      1778177700000,
      "MEASURED",
      34,
      2.0
    ],
    [
      1778177880000,
      "MEASURED",
      34,
      2.0
    ],
    [
      1778178060000,
      "MEASURED",
      34,
      2.0
    ],
    [
      1778178240000,
      "MEASURED",
      33,
      2.0
    ],
    [
      1778178420000,
      "MEASURED",
      33,
      2.0
    ],
    [
      1778178600000,
      "MEASURED",
      33,
      2.0
    ],
    [
      1778178780000,
      "MEASURED",
      33,
      2.0
    ],
    [
      1778178960000,
      "MEASURED",
      33,
      2.0
    ],
    [
      1778179140000,
      "MEASURED",
      33,
      2.0
    ],
    [
      1778179320000,
      "MEASURED",
      32,
      2.0
    ],
    [
      1778179500000,
      "MEASURED",
      32,
      2.0
    ],
    [
      1778179680000,
      "MEASURED",
      32,
      2.0
    ],
    [
      1778179860000,
      "MEASURED",
      32,
      2.0
    ],
    [
      1778180040000,
      "MEASURED",
      32,
      2.0
    ],
    [
      1778180220000,
      "MEASURED",
      32,
      2.0
    ],
    [
      1778180400000,
      "MEASURED",
      32,
      2.0
    ],
    [
      1778180580000,
      "MEASURED",
      31,
      2.0
    ],
    [
      1778180760000,
      "MEASURED",
      31,
      2.0
    ],
    [
      1778180940000,
      "MEASURED",
      31,
      2.0
    ],
    [
      1778181120000,
      "MEASURED",
      31,
      2.0
    ],
    [
      1778181300000,
      "MEASURED",
      30,
      2.0
    ],
    [
      1778181480000,
      "MEASURED",
      30,
      2.0
    ],
    [
      1778181660000,
      "MEASURED",
      30,
      2.0
    ],
    [
      1778181840000,
      "MEASURED",
      30,
      2.0
    ],
    [
      1778182020000,
      "MEASURED",
      30,
      2.0
    ],
    [
      1778182200000,
      "MEASURED",
      29,
      2.0
    ],
    [
      1778182380000,
      "MEASURED",
      29,
      2.0
    ],
    [
      1778182560000,
      "MEASURED",
      29,
      2.0
    ],
    [
      1778182740000,
      "MEASURED",
      29,
      2.0
    ],
    [
      1778182920000,
      "MEASURED",
      29,
      2.0
    ],
    [
      1778183100000,
      "MEASURED",
      29,
      2.0
    ],
    [
      1778183280000,
      "MEASURED",
      29,
      2.0
    ],
    [
      1778183460000,
      "MEASURED",
      29,
      2.0
    ],
    [
      1778183640000,
      "MEASURED",
      28,
      2.0
    ],
    [
      1778183820000,
      "MEASURED",
      28,
      2.0
    ],
    [
      1778184000000,
      "MEASURED",
      28,
      2.0
    ],
    [
      1778184180000,
      "MEASURED",
      28,
      2.0
    ],
    [
      1778184360000,
      "MEASURED",
      28,
      2.0
    ],
    [
      1778184540000,
      "MEASURED",
      28,
      2.0
    ],
    [
      1778184720000,
      "MEASURED",
      27,
      2.0
    ],
    [
      1778184900000,
      "MEASURED",
      27,
      2.0
    ],
    [
      1778185080000,
      "MEASURED",
      27,
      2.0
    ],
    [
      1778185260000,
      "MEASURED",
      27,
      2.0
    ],
    [
      1778185440000,
      "MEASURED",
      27,
      2.0
    ],
    [
      1778185620000,
      "MEASURED",
      27,
      2.0
    ],
    [
      1778185800000,
      "MEASURED",
      27,
      2.0
    ],
    [
      1778185980000,
      "MEASURED",
      27,
      2.0
    ],
    [
      1778186160000,
      "MEASURED",
      27,
      2.0
    ],
    [
      1778186340000,
      "MEASURED",
      27,
      2.0
    ],
    [
      1778186520000,
      "MEASURED",
      27,
      2.0
    ],
    [
      1778186700000,
      "MEASURED",
      27,
      2.0
    ],
    [
      1778186880000,
      "MEASURED",
      27,
      2.0
    ],
    [
      1778187060000,
      "MEASURED",
      27,
      2.0
    ],
    [
      1778187240000,
      "MEASURED",
      27,
      2.0
    ],
    [
      1778187420000,
      "MEASURED",
      27,
      2.0
    ],
    [
      1778187600000,
      "MEASURED",
      29,
      2.0
    ],
    [
      1778187780000,
      "MEASURED",
      29,
      2.0
    ],
    [
      1778187960000,
      "MEASURED",
      29,
      2.0
    ],
    [
      1778188140000,
      "MEASURED",
      29,
      2.0
    ],
    [
      1778188320000,
      "MEASURED",
      29,
      2.0
    ],
    [
      1778188500000,
      "MEASURED",
      29,
      2.0
    ],
    [
      1778188680000,
      "MEASURED",
      30,
      2.0
    ],
    [
      1778188860000,
      "MEASURED",
      30,
      2.0
    ],
    [
      1778189040000,
      "MEASURED",
      30,
      2.0
    ],
    [
      1778189220000,
      "MEASURED",
      30,
      2.0
    ],
    [
      1778189400000,
      "MEASURED",
      30,
      2.0
    ],
    [
      1778189580000,
      "MEASURED",
      30,
      2.0
    ],
    [
      1778189760000,
      "MEASURED",
      31,
      2.0
    ],
    [
      1778189940000,
      "MEASURED",
      31,
      2.0
    ],
    [
      1778190120000,
      "MEASURED",
      31,
      2.0
    ],
    [
      1778190300000,
      "MEASURED",
      31,
      2.0
    ],
    [
      1778190480000,
      "MEASURED",
      32,
      2.0
    ],
    [
      1778190660000,
      "MEASURED",
      32,
      2.0
    ],
    [
      1778190840000,
      "MEASURED",
      32,
      2.0
    ],
    [
      1778191020000,
      "MEASURED",
      32,
      2.0
    ]
  ]
}